Metadata-Version: 1.0
Name: amk-bipro
Version: 0.0.1
Summary: Gaussian distributions
Home-page: UNKNOWN
Author: Kololi Milimo
Author-email: kololimilimo@gmail.com
License: UNKNOWN
Platform: UNKNOWN
